<?xml version="1.0" encoding="UTF-8"?>
<!DOCTYPE struts PUBLIC
	"-//Apache Software Foundation//DTD Struts Configuration 2.3//EN"
	"http://struts.apache.org/dtds/struts-2.3.dtd">
<struts>
<package name="default" namespace="/" extends="struts-default">
	
    <action name="survey" class="SWE642_Vemuri.ActionClass">	
	<result name="simple_ack">SimpleAcknowledgement.jsp</result>
	<result name="winner_ack">WinnerAcknowledgement.jsp</result>
	<result name="student_info">StudentDetails.jsp</result>
	<result name="fail_to_find">NoSuchStudent.jsp</result>
	</action>
	
	<action name="student" class="SWE642_Vemuri.ActionClass" method="getMethod">
	<result name="student_info">StudentDetails.jsp</result>
	</action>

</package>
</struts>